README.md
setup.cfg
setup.py
wallaby_data_access/__init__.py
wallaby_data_access/wallaby.py
wallaby_data_access.egg-info/PKG-INFO
wallaby_data_access.egg-info/SOURCES.txt
wallaby_data_access.egg-info/dependency_links.txt
wallaby_data_access.egg-info/requires.txt
wallaby_data_access.egg-info/top_level.txt