Metadata-Version: 2.1
Name: wallaby-data-access
Version: 0.3.0
Summary: Module for accessing WALLABY internal release data 
Home-page: https://github.com/AusSRC/WALLABY_data_access
Author: Austin Shen
Author-email: austin.shen@csiro.au
Classifier: Development Status :: 2 - Pre-Alpha
Classifier: Programming Language :: Python :: 3
